[
  {
    "car_id": "252209",
    "car_name": "CLE 260 轿跑车",
    "price": "45.76万",
    "year": "2026",
    "series_name": "奔驰CLE级",
    "series_id": "6050",
    "brand_name": "奔驰",
    "brand": "奔驰",
    "level": "跑车",
    "energy_type": "",
    "is_target": true
  },
  {
    "car_id": "252210",
    "car_name": "CLE 300 4MATIC 动感型轿跑车",
    "price": "51.66万",
    "year": "2026",
    "series_name": "奔驰CLE级",
    "series_id": "6050",
    "brand_name": "奔驰",
    "brand": "奔驰",
    "level": "跑车",
    "energy_type": "",
    "is_target": true
  },
  {
    "car_id": "252211",
    "car_name": "CLE 300 4MATIC 豪华型轿跑车",
    "price": "55.58万",
    "year": "2026",
    "series_name": "奔驰CLE级",
    "series_id": "6050",
    "brand_name": "奔驰",
    "brand": "奔驰",
    "level": "跑车",
    "energy_type": "",
    "is_target": true
  },
  {
    "car_id": "252212",
    "car_name": "CLE 260 敞篷轿跑车",
    "price": "51.98万",
    "year": "2026",
    "series_name": "奔驰CLE级",
    "series_id": "6050",
    "brand_name": "奔驰",
    "brand": "奔驰",
    "level": "跑车",
    "energy_type": "",
    "is_target": true
  },
  {
    "car_id": "252213",
    "car_name": "CLE 300 4MATIC 敞篷轿跑车",
    "price": "59.98万",
    "year": "2026",
    "series_name": "奔驰CLE级",
    "series_id": "6050",
    "brand_name": "奔驰",
    "brand": "奔驰",
    "level": "跑车",
    "energy_type": "",
    "is_target": true
  },
  {
    "car_id": "244495",
    "car_name": "CLE 260 轿跑车",
    "price": "45.76万",
    "year": "2025",
    "series_name": "奔驰CLE级",
    "series_id": "6050",
    "brand_name": "奔驰",
    "brand": "奔驰",
    "level": "跑车",
    "energy_type": "",
    "is_target": true
  },
  {
    "car_id": "244496",
    "car_name": "CLE 300 4MATIC 动感型轿跑车",
    "price": "51.66万",
    "year": "2025",
    "series_name": "奔驰CLE级",
    "series_id": "6050",
    "brand_name": "奔驰",
    "brand": "奔驰",
    "level": "跑车",
    "energy_type": "",
    "is_target": true
  },
  {
    "car_id": "244502",
    "car_name": "CLE 260 敞篷轿跑车",
    "price": "51.98万",
    "year": "2025",
    "series_name": "奔驰CLE级",
    "series_id": "6050",
    "brand_name": "奔驰",
    "brand": "奔驰",
    "level": "跑车",
    "energy_type": "",
    "is_target": true
  },
  {
    "car_id": "244497",
    "car_name": "CLE 300 4MATIC 豪华型轿跑车",
    "price": "55.23万",
    "year": "2025",
    "series_name": "奔驰CLE级",
    "series_id": "6050",
    "brand_name": "奔驰",
    "brand": "奔驰",
    "level": "跑车",
    "energy_type": "",
    "is_target": true
  },
  {
    "car_id": "244503",
    "car_name": "CLE 300 4MATIC 敞篷轿跑车",
    "price": "59.63万",
    "year": "2025",
    "series_name": "奔驰CLE级",
    "series_id": "6050",
    "brand_name": "奔驰",
    "brand": "奔驰",
    "level": "跑车",
    "energy_type": "",
    "is_target": true
  },
  {
    "car_id": "252270",
    "car_name": "改款 AMG CLE 53 4MATIC+ 轿跑车",
    "price": "72.08万",
    "year": "2025",
    "series_name": "奔驰CLE级AMG",
    "series_id": "6051",
    "brand_name": "奔驰",
    "brand": "奔驰",
    "level": "跑车",
    "energy_type": "",
    "is_target": true
  },
  {
    "car_id": "101118",
    "car_name": "AMG CLE 53 4MATIC+ 敞篷轿跑车",
    "price": "78.00万",
    "year": "2025",
    "series_name": "奔驰CLE级AMG",
    "series_id": "6051",
    "brand_name": "奔驰",
    "brand": "奔驰",
    "level": "跑车",
    "energy_type": "",
    "is_target": true
  },
  {
    "car_id": "94354",
    "car_name": " AMG GT 63 S E PERFORMANCE",
    "price": "228.55万",
    "year": "2025",
    "series_name": "AMG GT PHEV",
    "series_id": "5009",
    "brand_name": "奔驰",
    "brand": "AMG",
    "level": "跑车",
    "energy_type": "",
    "is_target": true
  },
  {
    "car_id": "254992",
    "car_name": "AMG SL 63 4MATIC+",
    "price": "199.98万",
    "year": "2026",
    "series_name": "奔驰SL级AMG",
    "series_id": "262",
    "brand_name": "奔驰",
    "brand": "奔驰",
    "level": "跑车",
    "energy_type": "",
    "is_target": true
  },
  {
    "car_id": "55065",
    "car_name": "AMG SL 63 4MATIC+",
    "price": "199.98万",
    "year": "2024",
    "series_name": "奔驰SL级AMG",
    "series_id": "262",
    "brand_name": "奔驰",
    "brand": "奔驰",
    "level": "跑车",
    "energy_type": "",
    "is_target": true
  },
  {
    "car_id": "100374",
    "car_name": "2.0T 精英版 7座",
    "price": "33.68万",
    "year": "2024",
    "series_name": "威霆",
    "series_id": "244",
    "brand_name": "奔驰",
    "brand": "威霆",
    "level": "MPV",
    "energy_type": "",
    "is_target": true
  },
  {
    "car_id": "100475",
    "car_name": "2.0T 商务版 7座",
    "price": "38.68万",
    "year": "2024",
    "series_name": "威霆",
    "series_id": "244",
    "brand_name": "奔驰",
    "brand": "威霆",
    "level": "MPV",
    "energy_type": "",
    "is_target": true
  },
  {
    "car_id": "100473",
    "car_name": "2.0T 精英版 8座",
    "price": "33.68万",
    "year": "2024",
    "series_name": "威霆",
    "series_id": "244",
    "brand_name": "奔驰",
    "brand": "威霆",
    "level": "MPV",
    "energy_type": "",
    "is_target": true
  },
  {
    "car_id": "100476",
    "car_name": "2.0T 商务版 8座",
    "price": "38.68万",
    "year": "2024",
    "series_name": "威霆",
    "series_id": "244",
    "brand_name": "奔驰",
    "brand": "威霆",
    "level": "MPV",
    "energy_type": "",
    "is_target": true
  },
  {
    "car_id": "100474",
    "car_name": "2.0T 精英版 9座",
    "price": "34.58万",
    "year": "2024",
    "series_name": "威霆",
    "series_id": "244",
    "brand_name": "奔驰",
    "brand": "威霆",
    "level": "MPV",
    "energy_type": "",
    "is_target": true
  },
  {
    "car_id": "100477",
    "car_name": "2.0T 商务版 9座",
    "price": "38.68万",
    "year": "2024",
    "series_name": "威霆",
    "series_id": "244",
    "brand_name": "奔驰",
    "brand": "威霆",
    "level": "MPV",
    "energy_type": "",
    "is_target": true
  },
  {
    "car_id": "89810",
    "car_name": "2.0T 精英版 7座",
    "price": "29.38万",
    "year": "2023",
    "series_name": "威霆",
    "series_id": "244",
    "brand_name": "奔驰",
    "brand": "威霆",
    "level": "MPV",
    "energy_type": "",
    "is_target": true
  },
  {
    "car_id": "89813",
    "car_name": "2.0T 商务版 7座",
    "price": "35.48万",
    "year": "2023",
    "series_name": "威霆",
    "series_id": "244",
    "brand_name": "奔驰",
    "brand": "威霆",
    "level": "MPV",
    "energy_type": "",
    "is_target": true
  },
  {
    "car_id": "89811",
    "car_name": "2.0T 精英版 8座",
    "price": "29.38万",
    "year": "2023",
    "series_name": "威霆",
    "series_id": "244",
    "brand_name": "奔驰",
    "brand": "威霆",
    "level": "MPV",
    "energy_type": "",
    "is_target": true
  },
  {
    "car_id": "89814",
    "car_name": "2.0T 商务版 8座",
    "price": "35.48万",
    "year": "2023",
    "series_name": "威霆",
    "series_id": "244",
    "brand_name": "奔驰",
    "brand": "威霆",
    "level": "MPV",
    "energy_type": "",
    "is_target": true
  },
  {
    "car_id": "89812",
    "car_name": "2.0T 精英版 9座",
    "price": "30.28万",
    "year": "2023",
    "series_name": "威霆",
    "series_id": "244",
    "brand_name": "奔驰",
    "brand": "威霆",
    "level": "MPV",
    "energy_type": "",
    "is_target": true
  },
  {
    "car_id": "89815",
    "car_name": "2.0T 商务版 9座",
    "price": "35.48万",
    "year": "2023",
    "series_name": "威霆",
    "series_id": "244",
    "brand_name": "奔驰",
    "brand": "威霆",
    "level": "MPV",
    "energy_type": "",
    "is_target": true
  }
]